vpsearch/_vpsearch.cpython-37m-i386-linux-gnu.so
vpsearch/__init__.py
vpsearch/_cli.py
vpsearch/tests/test_vpsearch_cli.py
vpsearch/tests/__init__.py
vpsearch/tests/test_vpsearch.py
vpsearch-0.1.2.dist-info/LICENSE.txt
vpsearch-0.1.2.dist-info/WHEEL
vpsearch-0.1.2.dist-info/top_level.txt
vpsearch-0.1.2.dist-info/METADATA
vpsearch-0.1.2.dist-info/RECORD
vpsearch-0.1.2.dist-info/entry_points.txt
ci/__init__.py
ci/__main__.py
vpsearch.libs/libparasail-7aec56ce.so.3.4.2
