Metadata-Version: 2.1
Name: vpsearch
Version: 0.1.2
Summary: Global-Global genetic database search.
Home-page: https://github.com/enthought/vpsearch
Author: Enthought
Author-email: info@enthought.com
License: BSD
Platform: Linux
Platform: Mac OS-X
Platform: Unix
Classifier: Development Status :: 3 - Alpha
Classifier: Intended Audience :: Science/Research
Classifier: License :: OSI Approved :: BSD License
Classifier: Programming Language :: Python :: 3
Classifier: Programming Language :: Python :: 3.6
Classifier: Programming Language :: Python :: 3.7
Classifier: Programming Language :: Python :: 3.8
Classifier: Programming Language :: Python :: 3.9
Classifier: Programming Language :: Python :: 3.10
Classifier: Programming Language :: Cython
Classifier: Topic :: Scientific/Engineering
License-File: LICENSE.txt
Requires-Dist: click
Requires-Dist: numpy
